vishap/conf.py
vishap/discover.py
vishap/test.py
vishap/defaults.py
vishap/base.py
vishap/exceptions.py
vishap/utils.py
vishap/helpers.py
vishap/__init__.py
vishap/backports/collections.py
vishap/backports/__init__.py
vishap/contrib/__init__.py
vishap/contrib/apps/__init__.py
vishap/contrib/apps/django/__init__.py
vishap/contrib/apps/django/vishap/apps.py
vishap/contrib/apps/django/vishap/__init__.py
vishap/contrib/apps/django/vishap/templatetags/vishap_tags.py
vishap/contrib/apps/django/vishap/templatetags/__init__.py
vishap/contrib/plugins/__init__.py
vishap/contrib/plugins/vimeo/vishap_plugin.py
vishap/contrib/plugins/vimeo/__init__.py
vishap/contrib/plugins/youtube/vishap_plugin.py
vishap/contrib/plugins/youtube/__init__.py
vishap-0.1.5.dist-info/WHEEL
vishap-0.1.5.dist-info/DESCRIPTION.rst
vishap-0.1.5.dist-info/METADATA
vishap-0.1.5.dist-info/top_level.txt
vishap-0.1.5.dist-info/metadata.json
vishap-0.1.5.dist-info/RECORD
