Metadata-Version: 1.1
Name: vishap
Version: 0.1.5
Summary: Generate embed (HTML) code of services like Youtube or Vimeo from URLs given. Rules are specified in the plugins.
Home-page: https://github.com/barseghyanartur/vishap
Author: Artur Barseghyan
Author-email: artur.barseghyan@gmail.com
License: GPL 2.0/LGPL 2.1
Keywords: video,youtube,vimeo,video sharing services app
Platform: UNKNOWN
Classifier: Programming Language :: Python
Classifier: Programming Language :: Python :: 2.6
Classifier: Programming Language :: Python :: 2.7
Classifier: Programming Language :: Python :: 3
Classifier: Programming Language :: Python :: 3.3
Classifier: Intended Audience :: Developers
Classifier: Operating System :: OS Independent
Classifier: Development Status :: 4 - Beta
